plugenv/__init__.py
plugenv-0.0.0.dist-info/LICENSE
plugenv-0.0.0.dist-info/WHEEL
plugenv-0.0.0.dist-info/METADATA
plugenv-0.0.0.dist-info/RECORD
